xclingo/__init__.py
xclingo/__main__.py
xclingo/_arguments_handler.py
xclingo/_main.py
xclingo/_utils.py
xclingo/_version.py
xclingo/error/__init__.py
xclingo/explainer/__init__.py
xclingo/explainer/_explainer.py
xclingo/explainer/_logger.py
xclingo/explainer/_utils.py
xclingo/explainer/error/__init__.py
xclingo/explanation/__init__.py
xclingo/explanation/_graph.py
xclingo/extensions/__init__.py
xclingo/extensions/autotrace_all.lp
xclingo/extensions/autotrace_facts.lp
xclingo/extensions/graph_locals.lp
xclingo/extensions/graph_styles.lp
xclingo/extensions/violated_constraints_show_trace.lp
xclingo/preprocessor/__init__.py
xclingo/preprocessor/_pipeline.py
xclingo/preprocessor/_preprocessor.py
xclingo/preprocessor/_transformer.py
xclingo/preprocessor/_translator.py
xclingo/preprocessor/xclingo_ast/__init__.py
xclingo/preprocessor/xclingo_ast/_ast_shortcuts.py
xclingo/preprocessor/xclingo_ast/_xclingo_ast.py
xclingo/xclingo_lp/__init__.py
xclingo/xclingo_lp/causes.lp
xclingo/xclingo_lp/xclingo_fired.lp
xclingo/xclingo_lp/xclingo_graph.lp
xclingo/xclingo_lp/xclingo_show.lp
xclingo-2.0b19.dist-info/LICENSE
xclingo-2.0b19.dist-info/METADATA
xclingo-2.0b19.dist-info/WHEEL
xclingo-2.0b19.dist-info/entry_points.txt
xclingo-2.0b19.dist-info/top_level.txt
xclingo-2.0b19.dist-info/RECORD
