Metadata-Version: 2.1
Name: xclingo
Version: 2.0b19
Summary: Tool for explaining and debugging Answer Set Programs.
Home-page: https://github.com/bramucas/xclingo2
Author: Brais Muñiz
Author-email: mc.brais@gmail.com
License: UNKNOWN
Keywords: logic programming,answer set programming
Platform: UNKNOWN
Classifier: Programming Language :: Python :: 3
Classifier: License :: OSI Approved :: MIT License
Classifier: Operating System :: OS Independent
Requires-Python: >=3.8.0
License-File: LICENSE
Requires-Dist: argparse
Requires-Dist: clingo (>=5.5.0.post3)
Requires-Dist: clingraph
Requires-Dist: importlib-resources
